behave_to_cucumber/__init__.py
behave_to_cucumber/__main__.py
behave_to_cucumber-0.1.9.dist-info/entry_points.txt
behave_to_cucumber-0.1.9.dist-info/LICENSE
behave_to_cucumber-0.1.9.dist-info/WHEEL
behave_to_cucumber-0.1.9.dist-info/METADATA
behave_to_cucumber-0.1.9.dist-info/RECORD
