Metadata-Version: 2.1
Name: behave-to-cucumber
Version: 0.1.9
Summary: 该项目主要用于将behave框架生成的behave.json转换为cucumber.json
Home-page: https://github.com/chineseluo/behave_to_cucumber
Keywords: behave,cucumber,covert,BEHAVE,CUCUMBER
Author: chineseluo
Author-email: 848257135@qq.com
Requires-Python: >=3.7,<4.0
Classifier: Programming Language :: Python :: 3
Classifier: Programming Language :: Python :: 3.7
Classifier: Programming Language :: Python :: 3.8
Classifier: Programming Language :: Python :: 3.9
Requires-Dist: loguru (>=0.5.3,<0.6.0)
Project-URL: Repository, https://github.com/chineseluo/behave_to_cucumber
